gridbspline/__about__.py
gridbspline/__init__.py
gridbspline/_version.py
gridbspline/interpolate.py
gridbspline/maths.cpython-36m-darwin.so
gridbspline-1.0.0.dist-info/DESCRIPTION.rst
gridbspline-1.0.0.dist-info/METADATA
gridbspline-1.0.0.dist-info/RECORD
gridbspline-1.0.0.dist-info/WHEEL
gridbspline-1.0.0.dist-info/entry_points.txt
gridbspline-1.0.0.dist-info/metadata.json
gridbspline-1.0.0.dist-info/top_level.txt
