Metadata-Version: 2.0
Name: gridbspline
Version: 1.0.0
Summary: N-Dimensional, gridded, and multivariate data interpolation using splines
Home-page: http://gridbspline.readthedocs.org/
Author: Oscar Esteban
Author-email: code@oscaresteban.es
Maintainer-email: code@oscaresteban.es
License: Apache-2.0
Download-URL: https://github.com/oesteban/gridbspline/archive/1.0.0.tar.gz
Platform: UNKNOWN
Classifier: Development Status :: 3 - Alpha
Classifier: Intended Audience :: Science/Research
Classifier: Topic :: Scientific/Engineering :: Image Recognition
Classifier: License :: OSI Approved :: Apache Software License
Classifier: Programming Language :: Python :: 3.5
Classifier: Programming Language :: Python :: 3.6
Provides-Extra: all
Provides-Extra: doc
Provides-Extra: test
Requires-Dist: versioneer
Provides-Extra: all
Requires-Dist: imageio; extra == 'all'
Requires-Dist: pytest; extra == 'all'
Requires-Dist: sphinx (>=1.5.3); extra == 'all'
Requires-Dist: sphinx-rtd-theme (>=0.2.4); extra == 'all'
Provides-Extra: doc
Requires-Dist: imageio; extra == 'doc'
Requires-Dist: sphinx (>=1.5.3); extra == 'doc'
Requires-Dist: sphinx-rtd-theme (>=0.2.4); extra == 'doc'
Provides-Extra: test
Requires-Dist: pytest; extra == 'test'
